{
  "抖音": {
	"name": "douyin",
    "type": "image",
    "container": [
      {
        "icon": "111",
        "text": "111"
      },
      {
        "icon": "112",
        "text": "112"
      },
      {
        "icon": "113",
        "text": "113"
      },
      {
        "icon": "114",
        "text": "114"
      },
      {
        "icon": "11",
        "text": "11"
      },
      {
        "icon": "12",
        "text": "12"
      },
      {
        "icon": "13",
        "text": "13"
      },
      {
        "icon": "14",
        "text": "14"
      },
      {
        "icon": "15",
        "text": "15"
      },
      {
        "icon": "16",
        "text": "16"
      },
      {
        "icon": "17",
        "text": "17"
      },
      {
        "icon": "18",
        "text": "18"
      },
      {
        "icon": "19",
        "text": "19"
      },
      {
        "icon": "1",
        "text": "1"
      },
      {
        "icon": "20",
        "text": "20"
      },
      {
        "icon": "21",
        "text": "21"
      },
      {
        "icon": "22",
        "text": "22"
      },
      {
        "icon": "23",
        "text": "23"
      },
      {
        "icon": "24",
        "text": "24"
      },
      {
        "icon": "25",
        "text": "25"
      },
      {
        "icon": "26",
        "text": "26"
      },
      {
        "icon": "27",
        "text": "27"
      },
      {
        "icon": "28",
        "text": "28"
      },
      {
        "icon": "29",
        "text": "29"
      },
      {
        "icon": "2",
        "text": "2"
      },
      {
        "icon": "30",
        "text": "30"
      },
      {
        "icon": "31",
        "text": "31"
      },
      {
        "icon": "32",
        "text": "32"
      },
      {
        "icon": "33",
        "text": "33"
      },
      {
        "icon": "34",
        "text": "34"
      },
      {
        "icon": "35",
        "text": "35"
      },
      {
        "icon": "36",
        "text": "36"
      },
      {
        "icon": "37",
        "text": "37"
      },
      {
        "icon": "38",
        "text": "38"
      },
      {
        "icon": "39",
        "text": "39"
      },
      {
        "icon": "3",
        "text": "3"
      },
      {
        "icon": "40",
        "text": "40"
      },
      {
        "icon": "41",
        "text": "41"
      },
      {
        "icon": "42",
        "text": "42"
      },
      {
        "icon": "43",
        "text": "43"
      },
      {
        "icon": "44",
        "text": "44"
      },
      {
        "icon": "46",
        "text": "46"
      },
      {
        "icon": "47",
        "text": "47"
      },
      {
        "icon": "48",
        "text": "48"
      },
      {
        "icon": "49",
        "text": "49"
      },
      {
        "icon": "4",
        "text": "4"
      },
      {
        "icon": "50",
        "text": "50"
      },
      {
        "icon": "51",
        "text": "51"
      },
      {
        "icon": "52",
        "text": "52"
      },
      {
        "icon": "53",
        "text": "53"
      },
      {
        "icon": "54",
        "text": "54"
      },
      {
        "icon": "55",
        "text": "55"
      },
      {
        "icon": "57",
        "text": "57"
      },
      {
        "icon": "58",
        "text": "58"
      },
      {
        "icon": "59",
        "text": "59"
      },
      {
        "icon": "5",
        "text": "5"
      },
      {
        "icon": "60",
        "text": "60"
      },
      {
        "icon": "61",
        "text": "61"
      },
      {
        "icon": "62",
        "text": "62"
      },
      {
        "icon": "63",
        "text": "63"
      },
      {
        "icon": "64",
        "text": "64"
      },
      {
        "icon": "65",
        "text": "65"
      },
      {
        "icon": "66",
        "text": "66"
      },
      {
        "icon": "67",
        "text": "67"
      },
      {
        "icon": "69",
        "text": "69"
      },
      {
        "icon": "6",
        "text": "6"
      },
      {
        "icon": "72",
        "text": "72"
      },
      {
        "icon": "74",
        "text": "74"
      },
      {
        "icon": "76",
        "text": "76"
      },
      {
        "icon": "77",
        "text": "77"
      },
      {
        "icon": "78",
        "text": "78"
      },
      {
        "icon": "79",
        "text": "79"
      },
      {
        "icon": "7",
        "text": "7"
      },
      {
        "icon": "80",
        "text": "80"
      },
      {
        "icon": "81",
        "text": "81"
      },
      {
        "icon": "82",
        "text": "82"
      },
      {
        "icon": "85",
        "text": "85"
      },
      {
        "icon": "86",
        "text": "86"
      },
      {
        "icon": "87",
        "text": "87"
      },
      {
        "icon": "8",
        "text": "8"
      },
      {
        "icon": "90",
        "text": "90"
      },
      {
        "icon": "92",
        "text": "92"
      },
      {
        "icon": "93",
        "text": "93"
      },
      {
        "icon": "94",
        "text": "94"
      },
      {
        "icon": "95",
        "text": "95"
      },
      {
        "icon": "96",
        "text": "96"
      },
      {
        "icon": "97",
        "text": "97"
      },
      {
        "icon": "98",
        "text": "98"
      },
      {
        "icon": "99",
        "text": "99"
      },
      {
        "icon": "9",
        "text": "9"
      },
      {
        "icon": "all",
        "text": "all"
      },
      {
        "icon": "ba",
        "text": "ba"
      },
      {
        "icon": "bainian",
        "text": "bainian"
      },
      {
        "icon": "bianpao",
        "text": "bianpao"
      },
      {
        "icon": "bird",
        "text": "bird"
      },
      {
        "icon": "bulls",
        "text": "bulls"
      },
      {
        "icon": "chanche",
        "text": "chanche"
      },
      {
        "icon": "chepiao",
        "text": "chepiao"
      },
      {
        "icon": "chick",
        "text": "chick"
      },
      {
        "icon": "chinamoney",
        "text": "chinamoney"
      },
      {
        "icon": "drive",
        "text": "drive"
      },
      {
        "icon": "drug",
        "text": "drug"
      },
      {
        "icon": "eagle",
        "text": "eagle"
      },
      {
        "icon": "egg",
        "text": "egg"
      },
      {
        "icon": "eye",
        "text": "eye"
      },
      {
        "icon": "facai",
        "text": "facai"
      },
      {
        "icon": "feiji",
        "text": "feiji"
      },
      {
        "icon": "fengzheng",
        "text": "fengzheng"
      },
      {
        "icon": "flower",
        "text": "flower"
      },
      {
        "icon": "fu",
        "text": "fu"
      },
      {
        "icon": "gouliang",
        "text": "gouliang"
      },
      {
        "icon": "gouwuche",
        "text": "gouwuche"
      },
      {
        "icon": "greenhat",
        "text": "greenhat"
      },
      {
        "icon": "gu",
        "text": "gu"
      },
      {
        "icon": "guazi",
        "text": "guazi"
      },
      {
        "icon": "guihua",
        "text": "guihua"
      },
      {
        "icon": "hongbao",
        "text": "hongbao"
      },
      {
        "icon": "horse",
        "text": "horse"
      },
      {
        "icon": "huadeng",
        "text": "huadeng"
      },
      {
        "icon": "jiaozi",
        "text": "jiaozi"
      },
      {
        "icon": "jiu",
        "text": "jiu"
      },
      {
        "icon": "lingmeng",
        "text": "lingmeng"
      },
      {
        "icon": "longxia",
        "text": "longxia"
      },
      {
        "icon": "longzhou",
        "text": "longzhou"
      },
      {
        "icon": "mantou",
        "text": "mantou"
      },
      {
        "icon": "mushroom",
        "text": "mushroom"
      },
      {
        "icon": "needle",
        "text": "needle"
      },
      {
        "icon": "niulang",
        "text": "niulang"
      },
      {
        "icon": "noodle",
        "text": "noodle"
      },
      {
        "icon": "pipi",
        "text": "pipi"
      },
      {
        "icon": "qinglv",
        "text": "qinglv"
      },
      {
        "icon": "qingshu",
        "text": "qingshu"
      },
      {
        "icon": "qiqiu",
        "text": "qiqiu"
      },
      {
        "icon": "qiuye",
        "text": "qiuye"
      },
      {
        "icon": "shengridangao",
        "text": "shengridangao"
      },
      {
        "icon": "shu",
        "text": "shu"
      },
      {
        "icon": "shuijiao",
        "text": "shuijiao"
      },
      {
        "icon": "star",
        "text": "star"
      },
      {
        "icon": "tianyuebing",
        "text": "tianyuebing"
      },
      {
        "icon": "tianzong",
        "text": "tianzong"
      },
      {
        "icon": "tiger",
        "text": "tiger"
      },
      {
        "icon": "turtle",
        "text": "turtle"
      },
      {
        "icon": "tuzi",
        "text": "tuzi"
      },
      {
        "icon": "weishengzhi",
        "text": "weishengzhi"
      },
      {
        "icon": "wenhao",
        "text": "wenhao"
      },
      {
        "icon": "wocao",
        "text": "wocao"
      },
      {
        "icon": "xiandan",
        "text": "xiandan"
      },
      {
        "icon": "xianyuebing",
        "text": "xianyuebing"
      },
      {
        "icon": "xianzong",
        "text": "xianzong"
      },
      {
        "icon": "xique",
        "text": "xique"
      },
      {
        "icon": "yijianchuanxin",
        "text": "yijianchuanxin"
      }
    ]
  },
  "阿鲁": {
    "name": "arunew",
    "type": "image",
    "container": [
      {
        "icon": "aru-1",
        "text": "aru-1"
      },
      {
        "icon": "aru-10",
        "text": "aru-10"
      },
      {
        "icon": "aru-100",
        "text": "aru-100"
      },
      {
        "icon": "aru-101",
        "text": "aru-101"
      },
      {
        "icon": "aru-102",
        "text": "aru-102"
      },
      {
        "icon": "aru-103",
        "text": "aru-103"
      },
      {
        "icon": "aru-104",
        "text": "aru-104"
      },
      {
        "icon": "aru-105",
        "text": "aru-105"
      },
      {
        "icon": "aru-106",
        "text": "aru-106"
      },
      {
        "icon": "aru-107",
        "text": "aru-107"
      },
      {
        "icon": "aru-108",
        "text": "aru-108"
      },
      {
        "icon": "aru-109",
        "text": "aru-109"
      },
      {
        "icon": "aru-11",
        "text": "aru-11"
      },
      {
        "icon": "aru-110",
        "text": "aru-110"
      },
      {
        "icon": "aru-111",
        "text": "aru-111"
      },
      {
        "icon": "aru-112",
        "text": "aru-112"
      },
      {
        "icon": "aru-113",
        "text": "aru-113"
      },
      {
        "icon": "aru-114",
        "text": "aru-114"
      },
      {
        "icon": "aru-115",
        "text": "aru-115"
      },
      {
        "icon": "aru-116",
        "text": "aru-116"
      },
      {
        "icon": "aru-117",
        "text": "aru-117"
      },
      {
        "icon": "aru-118",
        "text": "aru-118"
      },
      {
        "icon": "aru-119",
        "text": "aru-119"
      },
      {
        "icon": "aru-12",
        "text": "aru-12"
      },
      {
        "icon": "aru-120",
        "text": "aru-120"
      },
      {
        "icon": "aru-121",
        "text": "aru-121"
      },
      {
        "icon": "aru-122",
        "text": "aru-122"
      },
      {
        "icon": "aru-123",
        "text": "aru-123"
      },
      {
        "icon": "aru-124",
        "text": "aru-124"
      },
      {
        "icon": "aru-125",
        "text": "aru-125"
      },
      {
        "icon": "aru-126",
        "text": "aru-126"
      },
      {
        "icon": "aru-127",
        "text": "aru-127"
      },
      {
        "icon": "aru-128",
        "text": "aru-128"
      },
      {
        "icon": "aru-129",
        "text": "aru-129"
      },
      {
        "icon": "aru-13",
        "text": "aru-13"
      },
      {
        "icon": "aru-130",
        "text": "aru-130"
      },
      {
        "icon": "aru-131",
        "text": "aru-131"
      },
      {
        "icon": "aru-132",
        "text": "aru-132"
      },
      {
        "icon": "aru-133",
        "text": "aru-133"
      },
      {
        "icon": "aru-134",
        "text": "aru-134"
      },
      {
        "icon": "aru-135",
        "text": "aru-135"
      },
      {
        "icon": "aru-136",
        "text": "aru-136"
      },
      {
        "icon": "aru-137",
        "text": "aru-137"
      },
      {
        "icon": "aru-138",
        "text": "aru-138"
      },
      {
        "icon": "aru-139",
        "text": "aru-139"
      },
      {
        "icon": "aru-14",
        "text": "aru-14"
      },
      {
        "icon": "aru-140",
        "text": "aru-140"
      },
      {
        "icon": "aru-141",
        "text": "aru-141"
      },
      {
        "icon": "aru-142",
        "text": "aru-142"
      },
      {
        "icon": "aru-143",
        "text": "aru-143"
      },
      {
        "icon": "aru-144",
        "text": "aru-144"
      },
      {
        "icon": "aru-145",
        "text": "aru-145"
      },
      {
        "icon": "aru-146",
        "text": "aru-146"
      },
      {
        "icon": "aru-147",
        "text": "aru-147"
      },
      {
        "icon": "aru-148",
        "text": "aru-148"
      },
      {
        "icon": "aru-149",
        "text": "aru-149"
      },
      {
        "icon": "aru-15",
        "text": "aru-15"
      },
      {
        "icon": "aru-150",
        "text": "aru-150"
      },
      {
        "icon": "aru-151",
        "text": "aru-151"
      },
      {
        "icon": "aru-152",
        "text": "aru-152"
      },
      {
        "icon": "aru-153",
        "text": "aru-153"
      },
      {
        "icon": "aru-154",
        "text": "aru-154"
      },
      {
        "icon": "aru-155",
        "text": "aru-155"
      },
      {
        "icon": "aru-156",
        "text": "aru-156"
      },
      {
        "icon": "aru-157",
        "text": "aru-157"
      },
      {
        "icon": "aru-158",
        "text": "aru-158"
      },
      {
        "icon": "aru-159",
        "text": "aru-159"
      },
      {
        "icon": "aru-16",
        "text": "aru-16"
      },
      {
        "icon": "aru-160",
        "text": "aru-160"
      },
      {
        "icon": "aru-161",
        "text": "aru-161"
      },
      {
        "icon": "aru-162",
        "text": "aru-162"
      },
      {
        "icon": "aru-163",
        "text": "aru-163"
      },
      {
        "icon": "aru-164",
        "text": "aru-164"
      },
      {
        "icon": "aru-165",
        "text": "aru-165"
      },
      {
        "icon": "aru-166",
        "text": "aru-166"
      },
      {
        "icon": "aru-167",
        "text": "aru-167"
      },
      {
        "icon": "aru-168",
        "text": "aru-168"
      },
      {
        "icon": "aru-169",
        "text": "aru-169"
      },
      {
        "icon": "aru-17",
        "text": "aru-17"
      },
      {
        "icon": "aru-170",
        "text": "aru-170"
      },
      {
        "icon": "aru-171",
        "text": "aru-171"
      },
      {
        "icon": "aru-172",
        "text": "aru-172"
      },
      {
        "icon": "aru-173",
        "text": "aru-173"
      },
      {
        "icon": "aru-174",
        "text": "aru-174"
      },
      {
        "icon": "aru-175",
        "text": "aru-175"
      },
      {
        "icon": "aru-176",
        "text": "aru-176"
      },
      {
        "icon": "aru-177",
        "text": "aru-177"
      },
      {
        "icon": "aru-178",
        "text": "aru-178"
      },
      {
        "icon": "aru-179",
        "text": "aru-179"
      },
      {
        "icon": "aru-18",
        "text": "aru-18"
      },
      {
        "icon": "aru-180",
        "text": "aru-180"
      },
      {
        "icon": "aru-181",
        "text": "aru-181"
      },
      {
        "icon": "aru-182",
        "text": "aru-182"
      },
      {
        "icon": "aru-183",
        "text": "aru-183"
      },
      {
        "icon": "aru-184",
        "text": "aru-184"
      },
      {
        "icon": "aru-185",
        "text": "aru-185"
      },
      {
        "icon": "aru-186",
        "text": "aru-186"
      },
      {
        "icon": "aru-187",
        "text": "aru-187"
      },
      {
        "icon": "aru-188",
        "text": "aru-188"
      },
      {
        "icon": "aru-189",
        "text": "aru-189"
      },
      {
        "icon": "aru-19",
        "text": "aru-19"
      },
      {
        "icon": "aru-190",
        "text": "aru-190"
      },
      {
        "icon": "aru-191",
        "text": "aru-191"
      },
      {
        "icon": "aru-192",
        "text": "aru-192"
      },
      {
        "icon": "aru-193",
        "text": "aru-193"
      },
      {
        "icon": "aru-194",
        "text": "aru-194"
      },
      {
        "icon": "aru-195",
        "text": "aru-195"
      },
      {
        "icon": "aru-196",
        "text": "aru-196"
      },
      {
        "icon": "aru-197",
        "text": "aru-197"
      },
      {
        "icon": "aru-198",
        "text": "aru-198"
      },
      {
        "icon": "aru-199",
        "text": "aru-199"
      },
      {
        "icon": "aru-2",
        "text": "aru-2"
      },
      {
        "icon": "aru-20",
        "text": "aru-20"
      },
      {
        "icon": "aru-200",
        "text": "aru-200"
      },
      {
        "icon": "aru-201",
        "text": "aru-201"
      },
      {
        "icon": "aru-202",
        "text": "aru-202"
      },
      {
        "icon": "aru-203",
        "text": "aru-203"
      },
      {
        "icon": "aru-204",
        "text": "aru-204"
      },
      {
        "icon": "aru-205",
        "text": "aru-205"
      },
      {
        "icon": "aru-206",
        "text": "aru-206"
      },
      {
        "icon": "aru-207",
        "text": "aru-207"
      },
      {
        "icon": "aru-208",
        "text": "aru-208"
      },
      {
        "icon": "aru-209",
        "text": "aru-209"
      },
      {
        "icon": "aru-21",
        "text": "aru-21"
      },
      {
        "icon": "aru-210",
        "text": "aru-210"
      },
      {
        "icon": "aru-211",
        "text": "aru-211"
      },
      {
        "icon": "aru-212",
        "text": "aru-212"
      },
      {
        "icon": "aru-213",
        "text": "aru-213"
      },
      {
        "icon": "aru-214",
        "text": "aru-214"
      },
      {
        "icon": "aru-215",
        "text": "aru-215"
      },
      {
        "icon": "aru-216",
        "text": "aru-216"
      },
      {
        "icon": "aru-217",
        "text": "aru-217"
      },
      {
        "icon": "aru-218",
        "text": "aru-218"
      },
      {
        "icon": "aru-219",
        "text": "aru-219"
      },
      {
        "icon": "aru-22",
        "text": "aru-22"
      },
      {
        "icon": "aru-220",
        "text": "aru-220"
      },
      {
        "icon": "aru-221",
        "text": "aru-221"
      },
      {
        "icon": "aru-222",
        "text": "aru-222"
      },
      {
        "icon": "aru-223",
        "text": "aru-223"
      },
      {
        "icon": "aru-224",
        "text": "aru-224"
      },
      {
        "icon": "aru-225",
        "text": "aru-225"
      },
      {
        "icon": "aru-226",
        "text": "aru-226"
      },
      {
        "icon": "aru-227",
        "text": "aru-227"
      },
      {
        "icon": "aru-228",
        "text": "aru-228"
      },
      {
        "icon": "aru-229",
        "text": "aru-229"
      },
      {
        "icon": "aru-23",
        "text": "aru-23"
      },
      {
        "icon": "aru-230",
        "text": "aru-230"
      },
      {
        "icon": "aru-231",
        "text": "aru-231"
      },
      {
        "icon": "aru-232",
        "text": "aru-232"
      },
      {
        "icon": "aru-233",
        "text": "aru-233"
      },
      {
        "icon": "aru-234",
        "text": "aru-234"
      },
      {
        "icon": "aru-235",
        "text": "aru-235"
      },
      {
        "icon": "aru-236",
        "text": "aru-236"
      },
      {
        "icon": "aru-237",
        "text": "aru-237"
      },
      {
        "icon": "aru-238",
        "text": "aru-238"
      },
      {
        "icon": "aru-239",
        "text": "aru-239"
      },
      {
        "icon": "aru-24",
        "text": "aru-24"
      },
      {
        "icon": "aru-240",
        "text": "aru-240"
      },
      {
        "icon": "aru-241",
        "text": "aru-241"
      },
      {
        "icon": "aru-242",
        "text": "aru-242"
      },
      {
        "icon": "aru-243",
        "text": "aru-243"
      },
      {
        "icon": "aru-244",
        "text": "aru-244"
      },
      {
        "icon": "aru-245",
        "text": "aru-245"
      },
      {
        "icon": "aru-246",
        "text": "aru-246"
      },
      {
        "icon": "aru-247",
        "text": "aru-247"
      },
      {
        "icon": "aru-248",
        "text": "aru-248"
      },
      {
        "icon": "aru-249",
        "text": "aru-249"
      },
      {
        "icon": "aru-25",
        "text": "aru-25"
      },
      {
        "icon": "aru-250",
        "text": "aru-250"
      },
      {
        "icon": "aru-251",
        "text": "aru-251"
      },
      {
        "icon": "aru-252",
        "text": "aru-252"
      },
      {
        "icon": "aru-253",
        "text": "aru-253"
      },
      {
        "icon": "aru-254",
        "text": "aru-254"
      },
      {
        "icon": "aru-255",
        "text": "aru-255"
      },
      {
        "icon": "aru-256",
        "text": "aru-256"
      },
      {
        "icon": "aru-257",
        "text": "aru-257"
      },
      {
        "icon": "aru-258",
        "text": "aru-258"
      },
      {
        "icon": "aru-259",
        "text": "aru-259"
      },
      {
        "icon": "aru-26",
        "text": "aru-26"
      },
      {
        "icon": "aru-260",
        "text": "aru-260"
      },
      {
        "icon": "aru-261",
        "text": "aru-261"
      },
      {
        "icon": "aru-262",
        "text": "aru-262"
      },
      {
        "icon": "aru-263",
        "text": "aru-263"
      },
      {
        "icon": "aru-264",
        "text": "aru-264"
      },
      {
        "icon": "aru-265",
        "text": "aru-265"
      },
      {
        "icon": "aru-266",
        "text": "aru-266"
      },
      {
        "icon": "aru-267",
        "text": "aru-267"
      },
      {
        "icon": "aru-268",
        "text": "aru-268"
      },
      {
        "icon": "aru-269",
        "text": "aru-269"
      },
      {
        "icon": "aru-27",
        "text": "aru-27"
      },
      {
        "icon": "aru-270",
        "text": "aru-270"
      },
      {
        "icon": "aru-271",
        "text": "aru-271"
      },
      {
        "icon": "aru-272",
        "text": "aru-272"
      },
      {
        "icon": "aru-273",
        "text": "aru-273"
      },
      {
        "icon": "aru-274",
        "text": "aru-274"
      },
      {
        "icon": "aru-275",
        "text": "aru-275"
      },
      {
        "icon": "aru-276",
        "text": "aru-276"
      },
      {
        "icon": "aru-277",
        "text": "aru-277"
      },
      {
        "icon": "aru-278",
        "text": "aru-278"
      },
      {
        "icon": "aru-279",
        "text": "aru-279"
      },
      {
        "icon": "aru-28",
        "text": "aru-28"
      },
      {
        "icon": "aru-280",
        "text": "aru-280"
      },
      {
        "icon": "aru-281",
        "text": "aru-281"
      },
      {
        "icon": "aru-282",
        "text": "aru-282"
      },
      {
        "icon": "aru-283",
        "text": "aru-283"
      },
      {
        "icon": "aru-284",
        "text": "aru-284"
      },
      {
        "icon": "aru-285",
        "text": "aru-285"
      },
      {
        "icon": "aru-286",
        "text": "aru-286"
      },
      {
        "icon": "aru-287",
        "text": "aru-287"
      },
      {
        "icon": "aru-288",
        "text": "aru-288"
      },
      {
        "icon": "aru-289",
        "text": "aru-289"
      },
      {
        "icon": "aru-29",
        "text": "aru-29"
      },
      {
        "icon": "aru-290",
        "text": "aru-290"
      },
      {
        "icon": "aru-291",
        "text": "aru-291"
      },
      {
        "icon": "aru-292",
        "text": "aru-292"
      },
      {
        "icon": "aru-293",
        "text": "aru-293"
      },
      {
        "icon": "aru-294",
        "text": "aru-294"
      },
      {
        "icon": "aru-295",
        "text": "aru-295"
      },
      {
        "icon": "aru-296",
        "text": "aru-296"
      },
      {
        "icon": "aru-297",
        "text": "aru-297"
      },
      {
        "icon": "aru-298",
        "text": "aru-298"
      },
      {
        "icon": "aru-299",
        "text": "aru-299"
      },
      {
        "icon": "aru-3",
        "text": "aru-3"
      },
      {
        "icon": "aru-30",
        "text": "aru-30"
      },
      {
        "icon": "aru-300",
        "text": "aru-300"
      },
      {
        "icon": "aru-301",
        "text": "aru-301"
      },
      {
        "icon": "aru-302",
        "text": "aru-302"
      },
      {
        "icon": "aru-303",
        "text": "aru-303"
      },
      {
        "icon": "aru-304",
        "text": "aru-304"
      },
      {
        "icon": "aru-305",
        "text": "aru-305"
      },
      {
        "icon": "aru-306",
        "text": "aru-306"
      },
      {
        "icon": "aru-31",
        "text": "aru-31"
      },
      {
        "icon": "aru-32",
        "text": "aru-32"
      },
      {
        "icon": "aru-33",
        "text": "aru-33"
      },
      {
        "icon": "aru-34",
        "text": "aru-34"
      },
      {
        "icon": "aru-35",
        "text": "aru-35"
      },
      {
        "icon": "aru-36",
        "text": "aru-36"
      },
      {
        "icon": "aru-37",
        "text": "aru-37"
      },
      {
        "icon": "aru-38",
        "text": "aru-38"
      },
      {
        "icon": "aru-39",
        "text": "aru-39"
      },
      {
        "icon": "aru-4",
        "text": "aru-4"
      },
      {
        "icon": "aru-40",
        "text": "aru-40"
      },
      {
        "icon": "aru-41",
        "text": "aru-41"
      },
      {
        "icon": "aru-42",
        "text": "aru-42"
      },
      {
        "icon": "aru-43",
        "text": "aru-43"
      },
      {
        "icon": "aru-44",
        "text": "aru-44"
      },
      {
        "icon": "aru-45",
        "text": "aru-45"
      },
      {
        "icon": "aru-46",
        "text": "aru-46"
      },
      {
        "icon": "aru-47",
        "text": "aru-47"
      },
      {
        "icon": "aru-48",
        "text": "aru-48"
      },
      {
        "icon": "aru-49",
        "text": "aru-49"
      },
      {
        "icon": "aru-5",
        "text": "aru-5"
      },
      {
        "icon": "aru-50",
        "text": "aru-50"
      },
      {
        "icon": "aru-51",
        "text": "aru-51"
      },
      {
        "icon": "aru-52",
        "text": "aru-52"
      },
      {
        "icon": "aru-53",
        "text": "aru-53"
      },
      {
        "icon": "aru-54",
        "text": "aru-54"
      },
      {
        "icon": "aru-55",
        "text": "aru-55"
      },
      {
        "icon": "aru-56",
        "text": "aru-56"
      },
      {
        "icon": "aru-57",
        "text": "aru-57"
      },
      {
        "icon": "aru-58",
        "text": "aru-58"
      },
      {
        "icon": "aru-59",
        "text": "aru-59"
      },
      {
        "icon": "aru-6",
        "text": "aru-6"
      },
      {
        "icon": "aru-60",
        "text": "aru-60"
      },
      {
        "icon": "aru-61",
        "text": "aru-61"
      },
      {
        "icon": "aru-62",
        "text": "aru-62"
      },
      {
        "icon": "aru-63",
        "text": "aru-63"
      },
      {
        "icon": "aru-64",
        "text": "aru-64"
      },
      {
        "icon": "aru-65",
        "text": "aru-65"
      },
      {
        "icon": "aru-66",
        "text": "aru-66"
      },
      {
        "icon": "aru-67",
        "text": "aru-67"
      },
      {
        "icon": "aru-68",
        "text": "aru-68"
      },
      {
        "icon": "aru-69",
        "text": "aru-69"
      },
      {
        "icon": "aru-7",
        "text": "aru-7"
      },
      {
        "icon": "aru-70",
        "text": "aru-70"
      },
      {
        "icon": "aru-71",
        "text": "aru-71"
      },
      {
        "icon": "aru-72",
        "text": "aru-72"
      },
      {
        "icon": "aru-73",
        "text": "aru-73"
      },
      {
        "icon": "aru-74",
        "text": "aru-74"
      },
      {
        "icon": "aru-75",
        "text": "aru-75"
      },
      {
        "icon": "aru-76",
        "text": "aru-76"
      },
      {
        "icon": "aru-77",
        "text": "aru-77"
      },
      {
        "icon": "aru-78",
        "text": "aru-78"
      },
      {
        "icon": "aru-79",
        "text": "aru-79"
      },
      {
        "icon": "aru-8",
        "text": "aru-8"
      },
      {
        "icon": "aru-80",
        "text": "aru-80"
      },
      {
        "icon": "aru-81",
        "text": "aru-81"
      },
      {
        "icon": "aru-82",
        "text": "aru-82"
      },
      {
        "icon": "aru-83",
        "text": "aru-83"
      },
      {
        "icon": "aru-84",
        "text": "aru-84"
      },
      {
        "icon": "aru-85",
        "text": "aru-85"
      },
      {
        "icon": "aru-86",
        "text": "aru-86"
      },
      {
        "icon": "aru-87",
        "text": "aru-87"
      },
      {
        "icon": "aru-88",
        "text": "aru-88"
      },
      {
        "icon": "aru-89",
        "text": "aru-89"
      },
      {
        "icon": "aru-9",
        "text": "aru-9"
      },
      {
        "icon": "aru-90",
        "text": "aru-90"
      },
      {
        "icon": "aru-91",
        "text": "aru-91"
      },
      {
        "icon": "aru-92",
        "text": "aru-92"
      },
      {
        "icon": "aru-93",
        "text": "aru-93"
      },
      {
        "icon": "aru-94",
        "text": "aru-94"
      },
      {
        "icon": "aru-95",
        "text": "aru-95"
      },
      {
        "icon": "aru-96",
        "text": "aru-96"
      },
      {
        "icon": "aru-97",
        "text": "aru-97"
      },
      {
        "icon": "aru-98",
        "text": "aru-98"
      },
      {
        "icon": "aru-99",
        "text": "aru-99"
      }
    ]
  },
    "萌表情": {
    "name": "face",
    "type": "image",
    "container": [
      {
        "icon": "hanxiao",
        "text": "憨笑"
      },
      {
        "icon": "guzhang",
        "text": "鼓掌"
      },
      {
        "icon": "motou",
        "text": "摸头"
      },
      {
        "icon": "biye",
        "text": "比耶"
      },
      {
        "icon": "dadaye",
        "text": "大大耶"
      },
      {
        "icon": "qinqin",
        "text": "亲亲"
      },
      {
        "icon": "huaigao",
        "text": "坏搞"
      },
      {
        "icon": "kelian",
        "text": "可怜"
      },
      {
        "icon": "tuxin",
        "text": "吐爱心"
      },
      {
        "icon": "wuyu",
        "text": "无语"
      },
      {
        "icon": "ganga",
        "text": "尴尬"
      },
      {
        "icon": "qifen",
        "text": "气愤"
      },
      {
        "icon": "shengqi",
        "text": "生气"
      },
      {
        "icon": "daku",
        "text": "大哭"
      },
      {
        "icon": "miaomiao",
        "text": "喵喵"
      },
      {
        "icon": "361",
        "text": "111"
      },
      {
        "icon": "362",
        "text": "112"
      },
      {
        "icon": "363",
        "text": "113"
      },
      {
        "icon": "364",
        "text": "114"
      },
      {
        "icon": "365",
        "text": "11"
      },
      {
        "icon": "366",
        "text": "12"
      },
      {
        "icon": "367",
        "text": "13"
      },
      {
        "icon": "368",
        "text": "14"
      },
      {
        "icon": "369",
        "text": "15"
      },
      {
        "icon": "370",
        "text": "16"
      },
      {
        "icon": "371",
        "text": "17"
      },
      {
        "icon": "372",
        "text": "18"
      },
      {
        "icon": "373",
        "text": "19"
      },
      {
        "icon": "374",
        "text": "1"
      },
      {
        "icon": "375",
        "text": "20"
      },
      {
        "icon": "376",
        "text": "21"
      },
      {
        "icon": "377",
        "text": "22"
      },
      {
        "icon": "378",
        "text": "23"
      },
      {
        "icon": "379",
        "text": "24"
      },
      {
        "icon": "380",
        "text": "25"
      },
      {
        "icon": "381",
        "text": "26"
      },
      {
        "icon": "382",
        "text": "27"
      },
      {
        "icon": "383",
        "text": "28"
      },
      {
        "icon": "384",
        "text": "29"
      },
      {
        "icon": "385",
        "text": "2"
      },
      {
        "icon": "386",
        "text": "30"
      },
      {
        "icon": "387",
        "text": "31"
      },
      {
        "icon": "388",
        "text": "32"
      },
      {
        "icon": "389",
        "text": "33"
      },
      {
        "icon": "390",
        "text": "34"
      },
      {
        "icon": "391",
        "text": "35"
      },
      {
        "icon": "392",
        "text": "36"
      },
      {
        "icon": "393",
        "text": "37"
      },
      {
        "icon": "394",
        "text": "38"
      },
      {
        "icon": "395",
        "text": "39"
      },
      {
        "icon": "396",
        "text": "3"
      },
      {
        "icon": "397",
        "text": "40"
      },
      {
        "icon": "398",
        "text": "41"
      },
      {
        "icon": "399",
        "text": "42"
      },
      {
        "icon": "400",
        "text": "43"
      },
       {
        "icon": "bp",
        "text": "111"
      },
      {
        "icon": "cc",
        "text": "112"
            },
            {
              "icon": "cdx",
              "text": "113"
            },
            {
              "icon": "dz",
              "text": "114"
            },
            {
              "icon": "fx",
              "text": "11"
            },
            {
              "icon": "qz",
              "text": "12"
            },
            {
              "icon": "sj",
              "text": "13"
            },
            {
              "icon": "sq",
              "text": "14"
            },
            {
              "icon": "xk",
              "text": "15"
            },
            {
              "icon": "xr",
              "text": "16"
            },
            {
              "icon": "xu",
              "text": "17"
            },
            {
              "icon": "yb",
              "text": "18"
            }
    ]
  },
  "bilibili":{
    "type": "image",
    "name": "bilibili",
    "container":[
      {
        "icon": "22_chijing",
        "text": "22_chijing"
      },
      {
        "icon": "22_daku",
        "text": "22_daku"
      },
      {
        "icon": "22_daxiao",
        "text": "22_daxiao"
      },
      {
        "icon": "22_nu",
        "text": "22_nu"
      },
      {
        "icon": "22_weiqu",
        "text": "22_weiqu"
      },
      {
        "icon": "22_yiwen",
        "text": "22_yiwen"
      },
      {
        "icon": "22_yumen",
        "text": "22_yumen"
      },
      {
        "icon": "33_han",
        "text": "33_han"
      },
      {
        "icon": "33_hecha",
        "text": "33_hecha"
      },
      {
        "icon": "33_maimeng",
        "text": "33_maimeng"
      },
      {
        "icon": "33_no1",
        "text": "33_no1"
      },
      {
        "icon": "33_tuhun",
        "text": "33_tuhun"
      },
      {
        "icon": "33_wuyan",
        "text": "33_wuyan"
      },
      {
        "icon": "33_yeah",
        "text": "33_yeah"
      },
      {
        "icon": "33_yiwen",
        "text": "33_yiwen"
      },
      {
        "icon": "ds_chaping",
        "text": "ds_chaping"
      },
      {
        "icon": "ds_chijing",
        "text": "ds_chijing"
      },
      {
        "icon": "ds_duzui",
        "text": "ds_duzui"
      },
      {
        "icon": "ds_fachou",
        "text": "ds_fachou"
      },
      {
        "icon": "ds_haixiu",
        "text": "ds_haixiu"
      },
      {
        "icon": "ds_han",
        "text": "ds_han"
      },
      {
        "icon": "ds_haonua",
        "text": "ds_haonua"
      },
      {
        "icon": "ds_kunhuo",
        "text": "ds_kunhuo"
      },
      {
        "icon": "ds_kuqi",
        "text": "ds_kuqi"
      },
      {
        "icon": "ds_sisuo",
        "text": "ds_sisuo"
      },
      {
        "icon": "ds_ttlike",
        "text": "ds_ttlike"
      },
      {
        "icon": "ds_wuyu",
        "text": "ds_wuyu"
      },
      {
        "icon": "ds_xf",
        "text": "ds_xf"
      },
      {
        "icon": "ds_xiao",
        "text": "ds_xiao"
      },
      {
        "icon": "ds_zan",
        "text": "ds_zan"
      },
      {
        "icon": "re_awsl",
        "text": "re_awsl"
      },
      {
        "icon": "re_bksn",
        "text": "re_bksn"
      },
      {
        "icon": "re_cb",
        "text": "re_cb"
      },
      {
        "icon": "re_chui",
        "text": "re_chui"
      },
      {
        "icon": "re_daka",
        "text": "re_daka"
      },
      {
        "icon": "re_gaochan",
        "text": "re_gaochan"
      },
      {
        "icon": "re_hai",
        "text": "re_hai"
      },
      {
        "icon": "re_keyi",
        "text": "re_keyi"
      },
      {
        "icon": "re_miao",
        "text": "re_miao"
      },
      {
        "icon": "re_mnbk",
        "text": "re_mnbk"
      },
      {
        "icon": "re_nxp",
        "text": "re_nxp"
      },
      {
        "icon": "re_olg",
        "text": "re_olg"
      },
      {
        "icon": "re_qgzs",
        "text": "re_qgzs"
      },
      {
        "icon": "re_suan",
        "text": "re_suan"
      },
      {
        "icon": "re_wkl",
        "text": "re_wkl"
      },
      {
        "icon": "re_wtnl",
        "text": "re_wtnl"
      },
      {
        "icon": "re_xiu",
        "text": "re_xiu"
      },
      {
        "icon": "re_ynwl",
        "text": "re_ynwl"
      },
      {
        "icon": "re_zsmq",
        "text": "re_zsmq"
      },
      {
        "icon": "re_zxa",
        "text": "re_zxa"
      }
    ]
  },
    "表情包": {
    "name": "bqb",
    "type": "image",
    "container": [
      {
        "icon": "niupi",
        "text": "牛皮"
      },
      {
        "icon": "jingyadee",
        "text": "惊讶"
      },
      {
        "icon": "dz",
        "text": "赞一个"
      },
      {
        "icon": "ppt",
        "text": "拍拍头"
      },
      {
        "icon": "gjdk",
        "text": "格局小了"
      },
      {
        "icon": "gejuda",
        "text": "格局大了"
      },
      {
        "icon": "gejulakua",
        "text": "格局拉胯"
      },
      {
        "icon": "cuoshoushou",
        "text": "搓手手"
      },
      {
        "icon": "xiemeiyixiao",
        "text": "邪魅一笑"
      },
      {
        "icon": "ziqiqiren",
        "text": "自欺欺人"
      },
      {
        "icon": "chixiangjiao",
        "text": "吃香蕉"
      },
      {
        "icon": "shengqi",
        "text": "咬死你"
      },
      {
        "icon": "chijing",
        "text": "吃惊的蕉太狼"
      },
      {
        "icon": "wuwu",
        "text": "呜呜呜"
      },
       {
        "icon": "pz",
        "text": "拍桌"
      },
      {
        "icon": "hd",
        "text": "非常火大"
      },
      {
        "icon": "sq",
        "text": "小脾气"
      },
       {
        "icon": "zhoumei",
        "text": "皱眉的小熊猫"
      },
       {
        "icon": "zhaosi",
        "text": "想被拍搬砖吗"
      },
       {
        "icon": "keyi",
        "text": "可以，没问题"
      },
      {
        "icon": "ztmynd",
        "text": "真他妈有你的"
      },
     
      {
        "icon": "bksn",
        "text": "不愧是你"
      },
      
      {
        "icon": "twdg",
        "text": "跳舞的狗"
      }
    ]
  }
}